{
  "engine": {
    "repo": "https://github.com/omni-scrna/boilerplate",
    "ref": "main",
    "commit": "8a8ba8524939b49db1179b2da5687f99cceeb91b",
    "version": null,
    "lang": "r"
  },
  "schemas": [
    {
      "benchmark": "split-stages",
      "repo": "https://github.com/omni-scrna/split-stages-plan",
      "ref": "new-stage-naming",
      "commit": "269fbb2429cce516633e06b02d371beea21c543c",
      "files": [
        "ANNO",
        "CLUST-M",
        "CLUST",
        "EMBED-M",
        "FEAT",
        "FILT",
        "INTG8",
        "NNG",
        "NORM",
        "PCA",
        "_base"
      ]
    }
  ],
  "fetched_at": "2026-06-20T15:28:23Z"
}
